engutils/__init__.py
engutils/engutils.py
engutils-21.8.dist-info/LICENSE
engutils-21.8.dist-info/METADATA
engutils-21.8.dist-info/WHEEL
engutils-21.8.dist-info/top_level.txt
engutils-21.8.dist-info/RECORD
